{"metric":{"slug":"bed-request-to-bed-assigned","label":"Bed Request \u2192 Bed Assigned","category":"Throughput","unit":"min","direction":"lower","description":"Inpatient team time to assign a bed.","subcomponent_slugs":[]},"slice":{"kind":"condition","name":"Chronic Kidney Disease"},"overall":350.57,"n_encounters":264,"monthly":[{"year_month":"2025-07","value":157.81,"forecast":null,"delta":null,"is_current_month":false,"days_observed":null,"days_in_month":31},{"year_month":"2025-08","value":227.0,"forecast":157.81,"delta":69.19,"is_current_month":false,"days_observed":null,"days_in_month":31},{"year_month":"2025-09","value":434.23,"forecast":192.41,"delta":241.82,"is_current_month":false,"days_observed":null,"days_in_month":30},{"year_month":"2025-10","value":317.45,"forecast":273.01,"delta":44.44,"is_current_month":false,"days_observed":null,"days_in_month":31},{"year_month":"2025-11","value":136.83,"forecast":284.12,"delta":-147.29,"is_current_month":false,"days_observed":null,"days_in_month":30},{"year_month":"2025-12","value":392.76,"forecast":254.66,"delta":138.1,"is_current_month":false,"days_observed":null,"days_in_month":31},{"year_month":"2026-01","value":296.3,"forecast":277.68,"delta":18.62,"is_current_month":false,"days_observed":null,"days_in_month":31},{"year_month":"2026-02","value":699.11,"forecast":300.76,"delta":398.35,"is_current_month":false,"days_observed":null,"days_in_month":28},{"year_month":"2026-03","value":617.03,"forecast":379.45,"delta":237.58,"is_current_month":false,"days_observed":null,"days_in_month":31},{"year_month":"2026-04","value":723.63,"forecast":409.91,"delta":313.72,"is_current_month":true,"days_observed":4.0,"days_in_month":30}],"quarterly":[{"fy_quarter":"FY26-Q1","value":251.63,"n":75},{"fy_quarter":"FY26-Q2","value":297.18,"n":104},{"fy_quarter":"FY26-Q3","value":479.31,"n":79},{"fy_quarter":"FY26-Q4","value":723.63,"n":6}],"by_location":[{"location":"ADULT ED","value":379.85,"n":175},{"location":"PEDS ED","value":54.74,"n":6},{"location":"KANAPAHA ED","value":172.22,"n":32},{"location":"SPRING ED","value":412.01,"n":32},{"location":"ONH ED","value":168.63,"n":19}],"by_condition":[],"subcomponents":[]}