{"metric":{"slug":"admit-rate","label":"Admit Rate","category":"Outcomes","unit":"pct","direction":"higher","description":"Share of encounters admitted to inpatient service.","subcomponent_slugs":[]},"slice":{"kind":"location","name":"SPRING ED"},"overall":14.38,"n_encounters":6948,"monthly":[{"year_month":"2023-07","value":16.31,"forecast":null,"delta":null,"is_current_month":false,"days_observed":null,"days_in_month":31},{"year_month":"2023-08","value":14.68,"forecast":16.31,"delta":-1.63,"is_current_month":false,"days_observed":null,"days_in_month":31},{"year_month":"2023-09","value":16.72,"forecast":15.49,"delta":1.23,"is_current_month":false,"days_observed":null,"days_in_month":30},{"year_month":"2023-10","value":13.04,"forecast":15.9,"delta":-2.86,"is_current_month":false,"days_observed":null,"days_in_month":31},{"year_month":"2023-11","value":14.87,"forecast":15.19,"delta":-0.32,"is_current_month":false,"days_observed":null,"days_in_month":30},{"year_month":"2023-12","value":11.25,"forecast":15.12,"delta":-3.87,"is_current_month":false,"days_observed":null,"days_in_month":31},{"year_month":"2024-01","value":13.68,"forecast":14.48,"delta":-0.8,"is_current_month":false,"days_observed":null,"days_in_month":31},{"year_month":"2024-02","value":15.61,"forecast":14.04,"delta":1.57,"is_current_month":false,"days_observed":null,"days_in_month":29},{"year_month":"2024-03","value":15.19,"forecast":14.2,"delta":0.99,"is_current_month":false,"days_observed":null,"days_in_month":31},{"year_month":"2024-04","value":13.29,"forecast":13.94,"delta":-0.65,"is_current_month":false,"days_observed":null,"days_in_month":30},{"year_month":"2024-05","value":13.44,"forecast":13.98,"delta":-0.54,"is_current_month":false,"days_observed":null,"days_in_month":31},{"year_month":"2024-06","value":14.67,"forecast":13.74,"delta":0.93,"is_current_month":false,"days_observed":null,"days_in_month":30}],"quarterly":[{"fy_quarter":"FY24-Q1","value":15.91,"n":1766},{"fy_quarter":"FY24-Q2","value":12.99,"n":1763},{"fy_quarter":"FY24-Q3","value":14.82,"n":1700},{"fy_quarter":"FY24-Q4","value":13.79,"n":1719}],"by_location":[],"by_condition":[{"condition":"Chest Pain (unspecified)","slug":"chest-pain-unspecified","value":22.27,"n":723},{"condition":"Abdominal Pain","slug":"abdominal-pain","value":16.99,"n":824},{"condition":"Upper Respiratory Infection","slug":"upper-respiratory-infection","value":2.16,"n":324},{"condition":"UTI","slug":"uti","value":18.78,"n":458},{"condition":"Arthritis/Musculoskeletal Pain","slug":"arthritis-musculoskeletal-pain","value":4.9,"n":347},{"condition":"Dehydration/Electrolyte Imbalance","slug":"dehydration-electrolyte-imbalance","value":36.73,"n":245},{"condition":"Cellulitis/Skin Infection","slug":"cellulitis-skin-infection","value":17.51,"n":257},{"condition":"Migraine/Headache","slug":"migraine-headache","value":3.26,"n":215},{"condition":"Anemia","slug":"anemia","value":50.88,"n":171},{"condition":"Hypertension","slug":"hypertension","value":23.67,"n":169},{"condition":"Traumatic Brain Injury","slug":"traumatic-brain-injury","value":1.18,"n":170},{"condition":"Fracture","slug":"fracture","value":12.23,"n":139},{"condition":"Alcohol Use Disorder","slug":"alcohol-use-disorder","value":40.91,"n":66},{"condition":"Epilepsy/Seizure","slug":"epilepsy-seizure","value":4.17,"n":24},{"condition":"Pneumonia","slug":"pneumonia","value":47.45,"n":137},{"condition":"Altered Mental Status","slug":"altered-mental-status","value":48.57,"n":70},{"condition":"Fever","slug":"fever","value":38.6,"n":57},{"condition":"COPD","slug":"copd","value":31.37,"n":102},{"condition":"Syncope","slug":"syncope","value":26.6,"n":94},{"condition":"Sepsis","slug":"sepsis","value":79.73,"n":74},{"condition":"Acute Kidney Injury","slug":"acute-kidney-injury","value":65.62,"n":128},{"condition":"Heart Failure","slug":"heart-failure","value":82.54,"n":63},{"condition":"Asthma","slug":"asthma","value":10.45,"n":67},{"condition":"Atrial Fibrillation","slug":"atrial-fibrillation","value":67.47,"n":83},{"condition":"Pregnancy/Childbirth","slug":"pregnancy-childbirth","value":7.27,"n":110},{"condition":"Substance Use Disorder (non-alcohol)","slug":"substance-use-disorder-non-alcohol","value":24.0,"n":50},{"condition":"Diabetes Mellitus","slug":"diabetes-mellitus","value":42.86,"n":77},{"condition":"Cancer/Malignant Neoplasm","slug":"cancer-malignant-neoplasm","value":66.67,"n":51},{"condition":"Chronic Kidney Disease","slug":"chronic-kidney-disease","value":34.62,"n":26},{"condition":"GI Hemorrhage","slug":"gi-hemorrhage","value":60.98,"n":41},{"condition":"Respiratory Failure","slug":"respiratory-failure","value":84.09,"n":44},{"condition":"Anxiety Disorders","slug":"anxiety-disorders","value":2.53,"n":79},{"condition":"Renal Stones","slug":"renal-stones","value":4.71,"n":85},{"condition":"Other Ischemic Heart Disease","slug":"other-ischemic-heart-disease","value":47.22,"n":36},{"condition":"Pulmonary Embolism/DVT","slug":"pulmonary-embolism-dvt","value":45.24,"n":42},{"condition":"Cardiac Arrhythmia (other)","slug":"cardiac-arrhythmia-other","value":53.19,"n":47},{"condition":"Stroke/CVA","slug":"stroke-cva","value":11.11,"n":18},{"condition":"Acute Bronchitis","slug":"acute-bronchitis","value":7.69,"n":13},{"condition":"Cholecystitis/Biliary Disease","slug":"cholecystitis-biliary-disease","value":16.67,"n":36},{"condition":"Poisoning/Overdose","slug":"poisoning-overdose","value":6.67,"n":15},{"condition":"Pancreatitis","slug":"pancreatitis","value":68.75,"n":64},{"condition":"AMI","slug":"ami","value":100.0,"n":14},{"condition":"Mood Disorders","slug":"mood-disorders","value":0.0,"n":17},{"condition":"Psychotic Disorders","slug":"psychotic-disorders","value":0.0,"n":4},{"condition":"Hypoglycemia","slug":"hypoglycemia","value":12.5,"n":8},{"condition":"Appendicitis","slug":"appendicitis","value":0.0,"n":5},{"condition":"Dementia/Cognitive","slug":"dementia-cognitive","value":50.0,"n":2}],"subcomponents":[]}