{"metric":{"slug":"bed-request-to-bed-assigned","label":"Bed Request \u2192 Bed Assigned","category":"Throughput","unit":"min","direction":"lower","description":"Inpatient team time to assign a bed.","subcomponent_slugs":[]},"slice":{"kind":"condition","name":"Asthma"},"overall":143.03,"n_encounters":542,"monthly":[{"year_month":"2023-07","value":173.46,"forecast":null,"delta":null,"is_current_month":false,"days_observed":null,"days_in_month":31},{"year_month":"2023-08","value":82.74,"forecast":173.46,"delta":-90.72,"is_current_month":false,"days_observed":null,"days_in_month":31},{"year_month":"2023-09","value":126.29,"forecast":128.1,"delta":-1.81,"is_current_month":false,"days_observed":null,"days_in_month":30},{"year_month":"2023-10","value":64.21,"forecast":127.5,"delta":-63.29,"is_current_month":false,"days_observed":null,"days_in_month":31},{"year_month":"2023-11","value":201.51,"forecast":111.67,"delta":89.84,"is_current_month":false,"days_observed":null,"days_in_month":30},{"year_month":"2023-12","value":128.79,"forecast":129.64,"delta":-0.85,"is_current_month":false,"days_observed":null,"days_in_month":31},{"year_month":"2024-01","value":328.01,"forecast":129.5,"delta":198.51,"is_current_month":false,"days_observed":null,"days_in_month":31},{"year_month":"2024-02","value":136.27,"forecast":155.26,"delta":-18.99,"is_current_month":false,"days_observed":null,"days_in_month":29},{"year_month":"2024-03","value":47.18,"forecast":164.18,"delta":-117.0,"is_current_month":false,"days_observed":null,"days_in_month":31},{"year_month":"2024-04","value":194.68,"forecast":150.99,"delta":43.69,"is_current_month":false,"days_observed":null,"days_in_month":30},{"year_month":"2024-05","value":171.1,"forecast":172.74,"delta":-1.64,"is_current_month":false,"days_observed":null,"days_in_month":31},{"year_month":"2024-06","value":64.79,"forecast":167.67,"delta":-102.88,"is_current_month":false,"days_observed":null,"days_in_month":30}],"quarterly":[{"fy_quarter":"FY24-Q1","value":125.24,"n":127},{"fy_quarter":"FY24-Q2","value":132.84,"n":168},{"fy_quarter":"FY24-Q3","value":167.52,"n":132},{"fy_quarter":"FY24-Q4","value":154.46,"n":115}],"by_location":[{"location":"ADULT ED","value":213.13,"n":123},{"location":"PEDS ED","value":69.91,"n":246},{"location":"KANAPAHA ED","value":149.58,"n":106},{"location":"SPRING ED","value":321.99,"n":67},{"location":"ONH ED","value":null,"n":0}],"by_condition":[],"subcomponents":[]}