{"metric":{"slug":"bed-ready-to-exit","label":"Bed Ready \u2192 Exit","category":"Throughput","unit":"min","direction":"lower","description":"Transport time from bed-ready notification to ED departure.","subcomponent_slugs":[]},"slice":{"kind":"condition","name":"Fever"},"overall":53.7,"n_encounters":673,"monthly":[{"year_month":"2024-07","value":40.48,"forecast":null,"delta":null,"is_current_month":false,"days_observed":null,"days_in_month":31},{"year_month":"2024-08","value":133.08,"forecast":40.48,"delta":92.6,"is_current_month":false,"days_observed":null,"days_in_month":31},{"year_month":"2024-09","value":35.64,"forecast":86.78,"delta":-51.14,"is_current_month":false,"days_observed":null,"days_in_month":30},{"year_month":"2024-10","value":54.36,"forecast":69.73,"delta":-15.37,"is_current_month":false,"days_observed":null,"days_in_month":31},{"year_month":"2024-11","value":44.62,"forecast":65.89,"delta":-21.27,"is_current_month":false,"days_observed":null,"days_in_month":30},{"year_month":"2024-12","value":45.62,"forecast":61.64,"delta":-16.02,"is_current_month":false,"days_observed":null,"days_in_month":31},{"year_month":"2025-01","value":47.9,"forecast":58.97,"delta":-11.07,"is_current_month":false,"days_observed":null,"days_in_month":31},{"year_month":"2025-02","value":55.29,"forecast":60.2,"delta":-4.91,"is_current_month":false,"days_observed":null,"days_in_month":28},{"year_month":"2025-03","value":40.85,"forecast":47.24,"delta":-6.39,"is_current_month":false,"days_observed":null,"days_in_month":31},{"year_month":"2025-04","value":44.94,"forecast":48.11,"delta":-3.17,"is_current_month":false,"days_observed":null,"days_in_month":30},{"year_month":"2025-05","value":73.15,"forecast":46.54,"delta":26.61,"is_current_month":false,"days_observed":null,"days_in_month":31},{"year_month":"2025-06","value":44.75,"forecast":51.29,"delta":-6.54,"is_current_month":false,"days_observed":null,"days_in_month":30}],"quarterly":[{"fy_quarter":"FY25-Q1","value":62.68,"n":139},{"fy_quarter":"FY25-Q2","value":47.71,"n":175},{"fy_quarter":"FY25-Q3","value":48.15,"n":168},{"fy_quarter":"FY25-Q4","value":55.98,"n":191}],"by_location":[{"location":"ADULT ED","value":53.51,"n":78},{"location":"PEDS ED","value":33.64,"n":461},{"location":"KANAPAHA ED","value":93.15,"n":63},{"location":"SPRING ED","value":126.5,"n":49},{"location":"ONH ED","value":142.2,"n":22}],"by_condition":[],"subcomponents":[]}