{"metric":{"slug":"boarding","label":"Boarding Time","category":"Throughput","unit":"min","direction":"lower","description":"Disposition \u2192 Exit. The time after a disposition is placed but before the patient physically leaves. Admit-bound patients dominate this.","subcomponent_slugs":["disposition-to-decision-to-admit","decision-to-admit-to-admit-order","admit-order-to-bed-request","bed-request-to-bed-assigned","bed-assigned-to-bed-ready","bed-ready-to-exit"]},"slice":{"kind":"condition","name":"Stroke/CVA"},"overall":225.38,"n_encounters":1165,"monthly":[{"year_month":"2024-07","value":171.76,"forecast":null,"delta":null,"is_current_month":false,"days_observed":null,"days_in_month":31},{"year_month":"2024-08","value":111.28,"forecast":171.76,"delta":-60.48,"is_current_month":false,"days_observed":null,"days_in_month":31},{"year_month":"2024-09","value":194.64,"forecast":141.52,"delta":53.12,"is_current_month":false,"days_observed":null,"days_in_month":30},{"year_month":"2024-10","value":169.03,"forecast":159.23,"delta":9.8,"is_current_month":false,"days_observed":null,"days_in_month":31},{"year_month":"2024-11","value":180.14,"forecast":161.68,"delta":18.46,"is_current_month":false,"days_observed":null,"days_in_month":30},{"year_month":"2024-12","value":233.64,"forecast":165.37,"delta":68.27,"is_current_month":false,"days_observed":null,"days_in_month":31},{"year_month":"2025-01","value":502.57,"forecast":176.75,"delta":325.82,"is_current_month":false,"days_observed":null,"days_in_month":31},{"year_month":"2025-02","value":518.38,"forecast":231.88,"delta":286.5,"is_current_month":false,"days_observed":null,"days_in_month":28},{"year_month":"2025-03","value":232.46,"forecast":299.73,"delta":-67.27,"is_current_month":false,"days_observed":null,"days_in_month":31},{"year_month":"2025-04","value":159.26,"forecast":306.04,"delta":-146.78,"is_current_month":false,"days_observed":null,"days_in_month":30},{"year_month":"2025-05","value":188.63,"forecast":304.41,"delta":-115.78,"is_current_month":false,"days_observed":null,"days_in_month":31},{"year_month":"2025-06","value":114.91,"forecast":305.82,"delta":-190.91,"is_current_month":false,"days_observed":null,"days_in_month":30}],"quarterly":[{"fy_quarter":"FY25-Q1","value":162.74,"n":354},{"fy_quarter":"FY25-Q2","value":190.93,"n":286},{"fy_quarter":"FY25-Q3","value":389.82,"n":296},{"fy_quarter":"FY25-Q4","value":151.47,"n":229}],"by_location":[{"location":"ADULT ED","value":269.69,"n":880},{"location":"PEDS ED","value":49.15,"n":17},{"location":"KANAPAHA ED","value":90.87,"n":134},{"location":"SPRING ED","value":68.97,"n":87},{"location":"ONH ED","value":74.2,"n":47}],"by_condition":[],"subcomponents":[{"slug":"disposition-to-decision-to-admit","label":"Disposition \u2192 Decision-to-Admit","unit":"min","value":0.0},{"slug":"decision-to-admit-to-admit-order","label":"Decision-to-Admit \u2192 Admit Order Written","unit":"min","value":109.86},{"slug":"admit-order-to-bed-request","label":"Admit Order \u2192 Bed Request","unit":"min","value":0.01},{"slug":"bed-request-to-bed-assigned","label":"Bed Request \u2192 Bed Assigned","unit":"min","value":180.23},{"slug":"bed-assigned-to-bed-ready","label":"Bed Assigned \u2192 Bed Ready","unit":"min","value":145.53},{"slug":"bed-ready-to-exit","label":"Bed Ready \u2192 Exit","unit":"min","value":48.4}]}