{"metric":{"slug":"door-to-disposition","label":"Door-to-Disposition","category":"Throughput","unit":"min","direction":"lower","description":"Arrival \u2192 disposition order.","subcomponent_slugs":[]},"slice":{"kind":"condition","name":"Poisoning/Overdose"},"overall":397.58,"n_encounters":229,"monthly":[{"year_month":"2023-07","value":317.09,"forecast":null,"delta":null,"is_current_month":false,"days_observed":null,"days_in_month":31},{"year_month":"2023-08","value":306.2,"forecast":317.09,"delta":-10.89,"is_current_month":false,"days_observed":null,"days_in_month":31},{"year_month":"2023-09","value":395.07,"forecast":311.64,"delta":83.43,"is_current_month":false,"days_observed":null,"days_in_month":30},{"year_month":"2023-10","value":439.64,"forecast":339.45,"delta":100.19,"is_current_month":false,"days_observed":null,"days_in_month":31},{"year_month":"2023-11","value":262.76,"forecast":364.5,"delta":-101.74,"is_current_month":false,"days_observed":null,"days_in_month":30},{"year_month":"2023-12","value":401.95,"forecast":344.15,"delta":57.8,"is_current_month":false,"days_observed":null,"days_in_month":31},{"year_month":"2024-01","value":442.06,"forecast":353.79,"delta":88.27,"is_current_month":false,"days_observed":null,"days_in_month":31},{"year_month":"2024-02","value":455.89,"forecast":374.61,"delta":81.28,"is_current_month":false,"days_observed":null,"days_in_month":29},{"year_month":"2024-03","value":402.71,"forecast":399.56,"delta":3.15,"is_current_month":false,"days_observed":null,"days_in_month":31},{"year_month":"2024-04","value":595.65,"forecast":400.83,"delta":194.82,"is_current_month":false,"days_observed":null,"days_in_month":30},{"year_month":"2024-05","value":352.68,"forecast":426.84,"delta":-74.16,"is_current_month":false,"days_observed":null,"days_in_month":31},{"year_month":"2024-06","value":446.03,"forecast":441.82,"delta":4.21,"is_current_month":false,"days_observed":null,"days_in_month":30}],"quarterly":[{"fy_quarter":"FY24-Q1","value":343.55,"n":74},{"fy_quarter":"FY24-Q2","value":379.28,"n":60},{"fy_quarter":"FY24-Q3","value":428.91,"n":52},{"fy_quarter":"FY24-Q4","value":476.96,"n":43}],"by_location":[{"location":"ADULT ED","value":482.85,"n":150},{"location":"PEDS ED","value":197.67,"n":33},{"location":"KANAPAHA ED","value":282.84,"n":31},{"location":"SPRING ED","value":208.46,"n":15},{"location":"ONH ED","value":null,"n":0}],"by_condition":[],"subcomponents":[]}