{"metric":{"slug":"inroom-to-md","label":"In-Room \u2192 MD","category":"Throughput","unit":"min","direction":"lower","description":"Time from arriving at the bed to first MD evaluation.","subcomponent_slugs":[]},"slice":{"kind":"condition","name":"Sepsis"},"overall":45.92,"n_encounters":641,"monthly":[{"year_month":"2019-07","value":52.35,"forecast":null,"delta":null,"is_current_month":false,"days_observed":null,"days_in_month":31},{"year_month":"2019-08","value":45.15,"forecast":52.35,"delta":-7.2,"is_current_month":false,"days_observed":null,"days_in_month":31},{"year_month":"2019-09","value":58.83,"forecast":48.75,"delta":10.08,"is_current_month":false,"days_observed":null,"days_in_month":30},{"year_month":"2019-10","value":36.9,"forecast":52.11,"delta":-15.21,"is_current_month":false,"days_observed":null,"days_in_month":31},{"year_month":"2019-11","value":49.5,"forecast":48.31,"delta":1.19,"is_current_month":false,"days_observed":null,"days_in_month":30},{"year_month":"2019-12","value":50.5,"forecast":48.55,"delta":1.95,"is_current_month":false,"days_observed":null,"days_in_month":31},{"year_month":"2020-01","value":37.23,"forecast":48.87,"delta":-11.64,"is_current_month":false,"days_observed":null,"days_in_month":31},{"year_month":"2020-02","value":61.94,"forecast":46.35,"delta":15.59,"is_current_month":false,"days_observed":null,"days_in_month":29},{"year_month":"2020-03","value":40.96,"forecast":49.15,"delta":-8.19,"is_current_month":false,"days_observed":null,"days_in_month":31},{"year_month":"2020-04","value":43.34,"forecast":46.17,"delta":-2.83,"is_current_month":false,"days_observed":null,"days_in_month":30},{"year_month":"2020-05","value":32.81,"forecast":47.25,"delta":-14.44,"is_current_month":false,"days_observed":null,"days_in_month":31},{"year_month":"2020-06","value":39.32,"forecast":44.46,"delta":-5.14,"is_current_month":false,"days_observed":null,"days_in_month":30}],"quarterly":[{"fy_quarter":"FY20-Q1","value":51.39,"n":192},{"fy_quarter":"FY20-Q2","value":45.37,"n":155},{"fy_quarter":"FY20-Q3","value":47.39,"n":137},{"fy_quarter":"FY20-Q4","value":38.34,"n":157}],"by_location":[{"location":"ADULT ED","value":51.84,"n":511},{"location":"PEDS ED","value":18.86,"n":23},{"location":"KANAPAHA ED","value":25.99,"n":59},{"location":"SPRING ED","value":18.86,"n":48},{"location":"ONH ED","value":null,"n":0}],"by_condition":[],"subcomponents":[]}