{"metric":{"slug":"inroom-to-md","label":"In-Room \u2192 MD","category":"Throughput","unit":"min","direction":"lower","description":"Time from arriving at the bed to first MD evaluation.","subcomponent_slugs":[]},"slice":{"kind":"condition","name":"Hypoglycemia"},"overall":45.31,"n_encounters":368,"monthly":[{"year_month":"2021-07","value":31.53,"forecast":null,"delta":null,"is_current_month":false,"days_observed":null,"days_in_month":31},{"year_month":"2021-08","value":44.81,"forecast":31.53,"delta":13.28,"is_current_month":false,"days_observed":null,"days_in_month":31},{"year_month":"2021-09","value":105.93,"forecast":38.17,"delta":67.76,"is_current_month":false,"days_observed":null,"days_in_month":30},{"year_month":"2021-10","value":33.74,"forecast":60.76,"delta":-27.02,"is_current_month":false,"days_observed":null,"days_in_month":31},{"year_month":"2021-11","value":40.53,"forecast":54.0,"delta":-13.47,"is_current_month":false,"days_observed":null,"days_in_month":30},{"year_month":"2021-12","value":34.09,"forecast":51.31,"delta":-17.22,"is_current_month":false,"days_observed":null,"days_in_month":31},{"year_month":"2022-01","value":49.2,"forecast":48.44,"delta":0.76,"is_current_month":false,"days_observed":null,"days_in_month":31},{"year_month":"2022-02","value":46.72,"forecast":51.38,"delta":-4.66,"is_current_month":false,"days_observed":null,"days_in_month":28},{"year_month":"2022-03","value":28.69,"forecast":51.7,"delta":-23.01,"is_current_month":false,"days_observed":null,"days_in_month":31},{"year_month":"2022-04","value":20.06,"forecast":38.83,"delta":-18.77,"is_current_month":false,"days_observed":null,"days_in_month":30},{"year_month":"2022-05","value":41.12,"forecast":36.55,"delta":4.57,"is_current_month":false,"days_observed":null,"days_in_month":31},{"year_month":"2022-06","value":14.15,"forecast":36.65,"delta":-22.5,"is_current_month":false,"days_observed":null,"days_in_month":30}],"quarterly":[{"fy_quarter":"FY22-Q1","value":72.32,"n":97},{"fy_quarter":"FY22-Q2","value":35.44,"n":79},{"fy_quarter":"FY22-Q3","value":41.88,"n":107},{"fy_quarter":"FY22-Q4","value":31.41,"n":85}],"by_location":[{"location":"ADULT ED","value":40.97,"n":240},{"location":"PEDS ED","value":26.4,"n":33},{"location":"KANAPAHA ED","value":16.29,"n":42},{"location":"SPRING ED","value":100.75,"n":53},{"location":"ONH ED","value":null,"n":0}],"by_condition":[],"subcomponents":[]}