{"metric":{"slug":"inroom-to-md","label":"In-Room \u2192 MD","category":"Throughput","unit":"min","direction":"lower","description":"Time from arriving at the bed to first MD evaluation.","subcomponent_slugs":[]},"slice":{"kind":"condition","name":"Renal Stones"},"overall":39.0,"n_encounters":277,"monthly":[{"year_month":"2025-07","value":36.86,"forecast":null,"delta":null,"is_current_month":false,"days_observed":null,"days_in_month":31},{"year_month":"2025-08","value":51.99,"forecast":36.86,"delta":15.13,"is_current_month":false,"days_observed":null,"days_in_month":31},{"year_month":"2025-09","value":56.54,"forecast":44.42,"delta":12.12,"is_current_month":false,"days_observed":null,"days_in_month":30},{"year_month":"2025-10","value":26.05,"forecast":48.46,"delta":-22.41,"is_current_month":false,"days_observed":null,"days_in_month":31},{"year_month":"2025-11","value":38.09,"forecast":42.86,"delta":-4.77,"is_current_month":false,"days_observed":null,"days_in_month":30},{"year_month":"2025-12","value":31.31,"forecast":41.91,"delta":-10.6,"is_current_month":false,"days_observed":null,"days_in_month":31},{"year_month":"2026-01","value":48.51,"forecast":40.14,"delta":8.37,"is_current_month":false,"days_observed":null,"days_in_month":31},{"year_month":"2026-02","value":18.27,"forecast":42.08,"delta":-23.81,"is_current_month":false,"days_observed":null,"days_in_month":28},{"year_month":"2026-03","value":29.03,"forecast":36.46,"delta":-7.43,"is_current_month":false,"days_observed":null,"days_in_month":31},{"year_month":"2026-04","value":7.76,"forecast":31.88,"delta":-24.12,"is_current_month":true,"days_observed":4.0,"days_in_month":30}],"quarterly":[{"fy_quarter":"FY26-Q1","value":47.44,"n":116},{"fy_quarter":"FY26-Q2","value":32.37,"n":89},{"fy_quarter":"FY26-Q3","value":35.0,"n":68},{"fy_quarter":"FY26-Q4","value":7.76,"n":4}],"by_location":[{"location":"ADULT ED","value":54.37,"n":130},{"location":"PEDS ED","value":34.67,"n":4},{"location":"KANAPAHA ED","value":19.44,"n":43},{"location":"SPRING ED","value":28.04,"n":48},{"location":"ONH ED","value":13.91,"n":52}],"by_condition":[],"subcomponents":[]}