{"metric":{"slug":"decision-to-admit-to-admit-order","label":"Decision-to-Admit \u2192 Admit Order Written","category":"Throughput","unit":"min","direction":"lower","description":"Provider-side time between deciding to admit and writing the admission order.","subcomponent_slugs":[]},"slice":{"kind":"condition","name":"Psychotic Disorders"},"overall":243.57,"n_encounters":147,"monthly":[{"year_month":"2022-07","value":null,"forecast":null,"delta":null,"is_current_month":false,"days_observed":null,"days_in_month":31},{"year_month":"2022-08","value":null,"forecast":null,"delta":null,"is_current_month":false,"days_observed":null,"days_in_month":31},{"year_month":"2022-09","value":175.64,"forecast":null,"delta":null,"is_current_month":false,"days_observed":null,"days_in_month":30},{"year_month":"2022-10","value":744.98,"forecast":175.64,"delta":569.34,"is_current_month":false,"days_observed":null,"days_in_month":31},{"year_month":"2022-11","value":113.82,"forecast":460.31,"delta":-346.49,"is_current_month":false,"days_observed":null,"days_in_month":30},{"year_month":"2022-12","value":304.28,"forecast":344.81,"delta":-40.53,"is_current_month":false,"days_observed":null,"days_in_month":31},{"year_month":"2023-01","value":204.73,"forecast":334.68,"delta":-129.95,"is_current_month":false,"days_observed":null,"days_in_month":31},{"year_month":"2023-02","value":null,"forecast":308.69,"delta":null,"is_current_month":false,"days_observed":null,"days_in_month":28},{"year_month":"2023-03","value":240.65,"forecast":308.69,"delta":-68.04,"is_current_month":false,"days_observed":null,"days_in_month":31},{"year_month":"2023-04","value":93.58,"forecast":321.69,"delta":-228.11,"is_current_month":false,"days_observed":null,"days_in_month":30},{"year_month":"2023-05","value":null,"forecast":191.41,"delta":null,"is_current_month":false,"days_observed":null,"days_in_month":31},{"year_month":"2023-06","value":17.32,"forecast":210.81,"delta":-193.49,"is_current_month":false,"days_observed":null,"days_in_month":30}],"quarterly":[{"fy_quarter":"FY23-Q1","value":175.64,"n":36},{"fy_quarter":"FY23-Q2","value":354.33,"n":40},{"fy_quarter":"FY23-Q3","value":222.69,"n":34},{"fy_quarter":"FY23-Q4","value":55.45,"n":37}],"by_location":[{"location":"ADULT ED","value":261.93,"n":122},{"location":"PEDS ED","value":null,"n":3},{"location":"KANAPAHA ED","value":59.92,"n":11},{"location":"SPRING ED","value":null,"n":11},{"location":"ONH ED","value":null,"n":0}],"by_condition":[],"subcomponents":[]}